sellsy_api/__init__.py
sellsy_api/__version__.py
sellsy_api/sellsy_client.py
sellsy_api/errors/__init__.py
sellsy_api/errors/sellsy_exceptions.py
sellsy_api-0.0.2.dist-info/LICENSE
sellsy_api-0.0.2.dist-info/METADATA
sellsy_api-0.0.2.dist-info/WHEEL
sellsy_api-0.0.2.dist-info/top_level.txt
sellsy_api-0.0.2.dist-info/RECORD
