Metadata-Version: 2.1
Name: sellsy-api
Version: 0.0.2
Summary: sellsy_api is a tiny client for Sellsy API
Home-page: https://github.com/Annouar/sellsy-api
Author: Annouar
Author-email: UNKNOWN
License: MIT
Project-URL: Bug Reports, https://github.com/Annouar/sellsy-client/issues
Keywords: Sellsy SellsyAPI SellsyClient sellsy_api sellsy_client
Platform: UNKNOWN
Requires-Dist: requests (>=2.21.0)
Requires-Dist: requests-oauthlib (>=1.2.0)
